cam2file/__init__.py
cam2file/core.py
cam2file/photographs.py
cam2file-0.0.1.dist-info/LICENSE
cam2file-0.0.1.dist-info/METADATA
cam2file-0.0.1.dist-info/WHEEL
cam2file-0.0.1.dist-info/top_level.txt
cam2file-0.0.1.dist-info/RECORD
