Metadata-Version: 2.1
Name: cam2file
Version: 0.0.1
Summary: Save the document in real world as the file using webcam.
Home-page: https://github.com/rtg0530/cam2file
Author: rtg0530
Author-email: rtg0530@gmail.com
Classifier: Programming Language :: Python :: 3
Classifier: License :: OSI Approved :: MIT License
Classifier: Operating System :: OS Independent
Requires-Python: >=3.7.4
License-File: LICENSE
